Metamorphic/MorphAlyt.c
Metamorphic/MorphAlyt.cp312-win_amd64.pyd
Metamorphic/data/F분포표(0.01).csv
Metamorphic/data/F분포표(0.1).csv
Metamorphic/data/Studentized Range q Table(0.01).csv
Metamorphic/data/Studentized Range q Table(0.05).csv
Metamorphic/data/chi.csv
Metamorphic/data/t분포표.csv
Metamorphic/data/표준정규분포표.csv
Metamorphic-0.1.3.dist-info/LICENSE
Metamorphic-0.1.3.dist-info/METADATA
Metamorphic-0.1.3.dist-info/WHEEL
Metamorphic-0.1.3.dist-info/top_level.txt
Metamorphic-0.1.3.dist-info/RECORD
