Metadata-Version: 2.1
Name: Metamorphic
Version: 0.1.3
Summary: Elliptic curve operations using SageMath
Author: fourchains_R&D
Author-email: fourchainsrd@gmail.com
Classifier: Programming Language :: Python :: 3
Classifier: Programming Language :: Cython
Classifier: License :: OSI Approved :: MIT License
Classifier: Operating System :: OS Independent
Requires-Python: >=3.6
License-File: LICENSE
Requires-Dist: pandas
Requires-Dist: numpy
Requires-Dist: scipy
Requires-Dist: sympy
Requires-Dist: matplotlib
Requires-Dist: seaborn
